poetry_plugin_freeze/__init__.py
poetry_plugin_freeze/app.py
poetry_plugin_freeze-1.1.0.dist-info/METADATA
poetry_plugin_freeze-1.1.0.dist-info/WHEEL
poetry_plugin_freeze-1.1.0.dist-info/entry_points.txt
poetry_plugin_freeze-1.1.0.dist-info/RECORD
