Metadata-Version: 2.1
Name: poetry-plugin-freeze
Version: 1.1.0
Summary: Poetry plugin to freeze a wheel's dependencies per lock file
Home-page: https://github.com/cloud-custodian/poetry-plugin-freeze
License: Apache-2.0
Author: Kapil Thangavelu
Author-email: kapilt@gmail.com
Requires-Python: >=3.9,<4.0
Classifier: License :: OSI Approved :: Apache Software License
Classifier: Programming Language :: Python :: 3
Classifier: Programming Language :: Python :: 3.9
Classifier: Programming Language :: Python :: 3.10
Classifier: Programming Language :: Python :: 3.11
Classifier: Programming Language :: Python :: 3.12
Classifier: Programming Language :: Python :: 3.13
Requires-Dist: poetry (>=1.3.0,<2.0.0)
Requires-Dist: poetry-core (>=1.3.0,<2.0.0)
